LICENSE
MANIFEST.in
README.md
crc4.c
crc4.pyi
py.typed
setup.py
.ccls-cache/@@home@ari@Ari@coding@projects_@crc4/@usr@include@bits@confname.h
.ccls-cache/@@home@ari@Ari@coding@projects_@crc4/@usr@include@bits@environments.h
.ccls-cache/@@home@ari@Ari@coding@projects_@crc4/@usr@include@bits@getopt_core.h
.ccls-cache/@@home@ari@Ari@coding@projects_@crc4/@usr@include@bits@getopt_posix.h
.ccls-cache/@@home@ari@Ari@coding@projects_@crc4/@usr@include@bits@long-double.h
.ccls-cache/@@home@ari@Ari@coding@projects_@crc4/@usr@include@bits@posix_opt.h
.ccls-cache/@@home@ari@Ari@coding@projects_@crc4/@usr@include@bits@time64.h
.ccls-cache/@@home@ari@Ari@coding@projects_@crc4/@usr@include@bits@timesize.h
.ccls-cache/@@home@ari@Ari@coding@projects_@crc4/@usr@include@bits@types.h
.ccls-cache/@@home@ari@Ari@coding@projects_@crc4/@usr@include@bits@typesizes.h
.ccls-cache/@@home@ari@Ari@coding@projects_@crc4/@usr@include@bits@unistd_ext.h
.ccls-cache/@@home@ari@Ari@coding@projects_@crc4/@usr@include@bits@wordsize.h
.ccls-cache/@@home@ari@Ari@coding@projects_@crc4/@usr@include@features-time64.h
.ccls-cache/@@home@ari@Ari@coding@projects_@crc4/@usr@include@features.h
.ccls-cache/@@home@ari@Ari@coding@projects_@crc4/@usr@include@gnu@stubs-64.h
.ccls-cache/@@home@ari@Ari@coding@projects_@crc4/@usr@include@gnu@stubs.h
.ccls-cache/@@home@ari@Ari@coding@projects_@crc4/@usr@include@stdc-predef.h
.ccls-cache/@@home@ari@Ari@coding@projects_@crc4/@usr@include@sys@cdefs.h
.ccls-cache/@@home@ari@Ari@coding@projects_@crc4/@usr@include@unistd.h
.ccls-cache/@@home@ari@Ari@coding@projects_@crc4/@usr@lib@clang@17@include@stddef.h
.ccls-cache/@home@ari@Ari@coding@projects_@crc4/crc4.c
.tox/.pkg/lib/python3.11/site-packages/pip/py.typed
.tox/.pkg/lib/python3.11/site-packages/pip/_vendor/cachecontrol/py.typed
.tox/.pkg/lib/python3.11/site-packages/pip/_vendor/certifi/py.typed
.tox/.pkg/lib/python3.11/site-packages/pip/_vendor/chardet/py.typed
crc4.egg-info/PKG-INFO
crc4.egg-info/SOURCES.txt
crc4.egg-info/dependency_links.txt
crc4.egg-info/top_level.txt
